odoo/addons/sale_partner_shipping_invoice_domain/README.rst
odoo/addons/sale_partner_shipping_invoice_domain/__init__.py
odoo/addons/sale_partner_shipping_invoice_domain/__manifest__.py
odoo/addons/sale_partner_shipping_invoice_domain/i18n/sale_partner_shipping_invoice_domain.pot
odoo/addons/sale_partner_shipping_invoice_domain/models/__init__.py
odoo/addons/sale_partner_shipping_invoice_domain/models/sale_order.py
odoo/addons/sale_partner_shipping_invoice_domain/readme/CONFIGURATION.rst
odoo/addons/sale_partner_shipping_invoice_domain/readme/CONTRIBUTORS.rst
odoo/addons/sale_partner_shipping_invoice_domain/readme/DESCRIPTION.rst
odoo/addons/sale_partner_shipping_invoice_domain/readme/USAGE.rst
odoo/addons/sale_partner_shipping_invoice_domain/static/description/icon.png
odoo/addons/sale_partner_shipping_invoice_domain/static/description/index.html
odoo/addons/sale_partner_shipping_invoice_domain/views/sale_order.xml
odoo14_addon_sale_partner_shipping_invoice_domain-14.0.1.0.2.dist-info/METADATA
odoo14_addon_sale_partner_shipping_invoice_domain-14.0.1.0.2.dist-info/WHEEL
odoo14_addon_sale_partner_shipping_invoice_domain-14.0.1.0.2.dist-info/top_level.txt
odoo14_addon_sale_partner_shipping_invoice_domain-14.0.1.0.2.dist-info/RECORD
